houseteli_administrator/__init__.py
houseteli_administrator/admin/__init__.py
houseteli_administrator/admin/adapter.py
houseteli_administrator/admin/admin.py
houseteli_administrator/admin/apps.py
houseteli_administrator/admin/backends.py
houseteli_administrator/admin/middleware.py
houseteli_administrator/admin/models.py
houseteli_administrator/admin/serializers.py
houseteli_administrator/admin/urls.py
houseteli_administrator/admin/utils.py
houseteli_administrator/admin/views.py
houseteli_administrator/admin/management/__init__.py
houseteli_administrator/admin/management/commands/__init__.py
houseteli_administrator/admin/management/commands/identity_defaults.py
houseteli_administrator/admin/migrations/0001_initial.py
houseteli_administrator/admin/migrations/__init__.py
houseteli_administrator/auth/__init__.py
houseteli_administrator/auth/adapter.py
houseteli_administrator/auth/apps.py
houseteli_administrator/auth/serializers.py
houseteli_administrator/auth/urls.py
houseteli_administrator/auth/views.py
houseteli_administrator/h_admin/__init__.py
houseteli_administrator/h_admin/adapter.py
houseteli_administrator/h_admin/admin.py
houseteli_administrator/h_admin/apps.py
houseteli_administrator/h_admin/backends.py
houseteli_administrator/h_admin/middleware.py
houseteli_administrator/h_admin/models.py
houseteli_administrator/h_admin/serializers.py
houseteli_administrator/h_admin/urls.py
houseteli_administrator/h_admin/utils.py
houseteli_administrator/h_admin/views.py
houseteli_administrator/h_admin/management/__init__.py
houseteli_administrator/h_admin/management/commands/__init__.py
houseteli_administrator/h_admin/management/commands/identity_defaults.py
houseteli_administrator/h_admin/migrations/0001_initial.py
houseteli_administrator/h_admin/migrations/__init__.py
houseteli_administrator/h_auth/__init__.py
houseteli_administrator/h_auth/adapter.py
houseteli_administrator/h_auth/apps.py
houseteli_administrator/h_auth/serializers.py
houseteli_administrator/h_auth/urls.py
houseteli_administrator-0.1.14.dist-info/METADATA
houseteli_administrator-0.1.14.dist-info/WHEEL
houseteli_administrator-0.1.14.dist-info/top_level.txt
houseteli_administrator-0.1.14.dist-info/RECORD
