Metadata-Version: 2.1
Name: houseteli_administrator
Version: 0.1.14
Summary: Helpers for houseteli microservices which use django
Home-page: https://houseteli.github.io
Author: Brian Onang'o
Author-email: surgbc@gmail.com
Project-URL: Homepage, https://github.com/houseteli/houseteli_administrator
Project-URL: Issues, https://github.com/houseteli/houseteli_administrator/issues
Classifier: Programming Language :: Python :: 3
Classifier: License :: OSI Approved :: MIT License
Classifier: Operating System :: OS Independent
Requires-Python: >=3.6
